mysqlparse/__init__.py
mysqlparse/grammar/__init__.py
mysqlparse/grammar/alter_table.py
mysqlparse/grammar/column_definition.py
mysqlparse/grammar/data_type.py
mysqlparse/grammar/grammar.py
mysqlparse/grammar/sql_file.py
mysqlparse/grammar/utils.py
mysqlparse-0.1.5.dist-info/DESCRIPTION.rst
mysqlparse-0.1.5.dist-info/METADATA
mysqlparse-0.1.5.dist-info/RECORD
mysqlparse-0.1.5.dist-info/WHEEL
mysqlparse-0.1.5.dist-info/metadata.json
mysqlparse-0.1.5.dist-info/top_level.txt
