Metadata-Version: 2.0
Name: mysqlparse
Version: 0.1.5
Summary: A library for parsing SQL statements.
Home-page: https://github.com/seporaitis/mysqlparse
Author: Julius Seporaitis
Author-email: julius@seporaitis.net
License: MIT
Keywords: sql parse pyparsing mysql database
Platform: UNKNOWN
Classifier: Development Status :: 3 - Alpha
Classifier: Intended Audience :: Developers
Classifier: License :: OSI Approved :: MIT License
Classifier: Natural Language :: English
Classifier: Programming Language :: Python :: 2
Classifier: Programming Language :: Python :: 2.7
Classifier: Programming Language :: Python :: 3
Classifier: Programming Language :: Python :: 3.3
Classifier: Programming Language :: Python :: 3.4
Classifier: Programming Language :: Python :: 3.5
Requires-Dist: pyparsing
Requires-Dist: six
